onebeans_bmi/bmi.py
onebeans_bmi-0.0.0.1.dist-info/METADATA
onebeans_bmi-0.0.0.1.dist-info/WHEEL
onebeans_bmi-0.0.0.1.dist-info/top_level.txt
onebeans_bmi-0.0.0.1.dist-info/RECORD
